{
  "hero": {
    "tag": "Hub Competitif Pokemon",
    "title": "L'actu competitive en un seul endroit."
  },
  "news": [
    {
      "game": "tcgp",
      "title": "Mega Altaria ex Espeon en tete du meta Pocket",
      "desc": "Le métagame Paradox Drive se cristallise autour d'un duel permanent entre vitesse et contrôle. Mega Altaria ex Espeon règne toujours en maître avec 8,53% d'usage, mais son winrate anémique à 50,25% révèle sa vulnérabilité face aux decks Water dominants. Suicune ex Baxcalibur (53,35% WR) et Mega Blaziken ex Greninja (53,12% WR) s'imposent comme les vrais prédateurs du format, exploitant la faiblesse généralisée au type Eau. Les variantes Magnezone continuent leur prolifération schizophrénique avec trois builds distincts dans le top 10, témoignant d'une recherche constante d'optimisation sans consensus clair.",
      "when": "TCG Pocket",
      "badgeText": "META",
      "badgeStyle": "tcgp",
      "clickAction": "tcgp"
    },
    {
      "game": "vgc",
      "title": "VGC — etat du format",
      "desc": "La méta Regulation M-A est dominée par un trio hyper-stable : Kingambit/Garchomp/Basculegion apparaissent dans plus de 50% des équipes et forment le cœur d'un archétype Tailwind/beatdown extrêmement populaire. L'émergence d'Eternal Flower Floette (42,66%) avec sa méga-évolution Floettite crée une seconde dimension stratégique axée sur le setup et la sustain, souvent accompagnée d'Incineroar/Sinistcha pour former un core Trick Room redoutable. Les méga-évolutions (Charizard Y à 90%, Dragonite avec Dragoninite, Aerodactyl) définissent les win conditions, avec une préférence marquée pour les stratégies de speed control via Tailwind (Whimsicott, Aerodactyl) ou Trick Room (Sinistcha). Les victoires récentes de Hiroshi Onishi aux JCS confirment la viabilité d'équipes équilibrées combinant pression offensive immédiate et capacité de setup.",
      "when": "Regulation Set M-A",
      "badgeText": "VGC",
      "badgeStyle": "vgc",
      "clickAction": "vgc"
    },
    {
      "game": "unite",
      "title": "Unite — Patch 1.23.3.2 — bugfixes and Meganium (2026-05-28)",
      "desc": "Patch 1.23.3.2 — Alcremie (A+) en tête.",
      "when": "Pokémon Unite",
      "badgeText": "UNITE",
      "badgeStyle": "unite",
      "clickAction": "unite"
    }
  ],
  "timeline": [
    {
      "title": "Pocket Battle League — Saison 1",
      "desc": "tcgp",
      "game": "tcgp"
    },
    {
      "title": "Imperium Championship — Saison 1",
      "desc": "tcgp",
      "game": "tcgp"
    }
  ],
  "gamePreviews": {
    "tcgp": true,
    "vgc": true,
    "classic": true,
    "unite": true
  },
  "updatedAt": "2026-06-10T06:02:29.470Z"
}