{
"metaSummary": "La méta reste dominée par Miraidon ex Magnezone en usage avec 7 631 joueurs sur 89 tournois et 20 042 matchs analysés cette semaine (10,17 % usage, 52,98 % WR), toujours suivi par Greninja Mega Sableye ex (6,51 % usage, 47,19 % WR, toujours le point faible du top 3). Le top 10 usage reste parfaitement stable par rapport à hier : Suicune ex Baxcalibur conserve la 3e place (6,37 %, 52,62 % WR) devant Mega Sceptile ex Greninja (6,20 %, 52,27 % WR). Côté winrate en revanche, gros chamboulement en tête : Giratina ex Darkrai ex fait une entrée fracassante à la 1re place (0,55 % usage, 55,17 % WR), reléguant Milotic ex Eevee ex (54,65 % WR) et Greninja Mega Absol ex (54,62 % WR) aux 2e et 3e places, tandis que Gourgeist Houndstone (52,75 % WR) et Magnezone ex Magnezone (52,38 % WR) font aussi leur entrée dans le top 10, faisant sortir Mega Sceptile ex Greninja, Magnezone Miraidon ex et Mega Manectric ex Zeraora. Plus que 7 jours avant le lancement de Ruler of the Skies (B4, 30 juillet), avec Mega Rayquaza ex en vedette.",
"metaSummary_en": "The meta remains dominated by Miraidon ex Magnezone in usage with 7,631 players across 89 tournaments and 20,042 matches analyzed this week (10.17% usage, 52.98% win rate), still followed by Greninja Mega Sableye ex (6.51% usage, 47.19% win rate, still the weak point of the top 3). The usage top 10 is perfectly stable compared to yesterday: Suicune ex Baxcalibur holds 3rd place (6.37%, 52.62% win rate) ahead of Mega Sceptile ex Greninja (6.20%, 52.27% win rate). On the win-rate side, however, there's a major shake-up at the top: Giratina ex Darkrai ex bursts into 1st place (0.55% usage, 55.17% win rate), pushing Milotic ex Eevee ex (54.65% win rate) and Greninja Mega Absol ex (54.62% win rate) down to 2nd and 3rd, while Gourgeist Houndstone (52.75% win rate) and Magnezone ex Magnezone (52.38% win rate) also break into the top 10, knocking out Mega Sceptile ex Greninja, Magnezone Miraidon ex and Mega Manectric ex Zeraora. Just 7 days remain before the launch of Ruler of the Skies (B4) on July 30, starring Mega Rayquaza ex.",
"topUsage": [
{
"rank": 1,
"name": "Miraidon ex Magnezone",
"usage": 10.17,
"winrate": 52.98,
"record": "2340-1914-163",
"move": "same",
"limitless": "miraidon-ex-b3a-magnezone-b1a",
"winRate": 52.98,
"share": 10.17
},
{
"rank": 2,
"name": "Greninja Mega Sableye ex",
"usage": 6.51,
"winrate": 47.19,
"record": "1224-1295-75",
"move": "same",
"limitless": "greninja-a1-mega-sableye-ex-b3b",
"winRate": 47.19,
"share": 6.51
},
{
"rank": 3,
"name": "Suicune ex Baxcalibur",
"usage": 6.37,
"winrate": 52.62,
"record": "1415-1183-91",
"move": "same",
"limitless": "suicune-ex-a4a-baxcalibur-b2a",
"winRate": 52.62,
"share": 6.37
},
{
"rank": 4,
"name": "Mega Sceptile ex Greninja",
"usage": 6.20,
"winrate": 52.27,
"record": "1403-1198-83",
"move": "same",
"limitless": "mega-sceptile-ex-b3-greninja-a1",
"winRate": 52.27,
"share": 6.20
},
{
"rank": 5,
"name": "Mega Lucario ex Lucario",
"usage": 5.14,
"winrate": 50.78,
"record": "1138-1020-83",
"move": "same",
"limitless": "mega-lucario-ex-b3-lucario-a2",
"winRate": 50.78,
"share": 5.14
},
{
"rank": 6,
"name": "Butterfree Mega Sceptile ex",
"usage": 3.84,
"winrate": 48.08,
"record": "752-765-47",
"move": "same",
"limitless": "butterfree-b3b-mega-sceptile-ex-b3",
"winRate": 48.08,
"share": 3.84
},
{
"rank": 7,
"name": "Mega Blaziken ex Greninja",
"usage": 3.30,
"winrate": 53.16,
"record": "766-632-43",
"move": "same",
"limitless": "mega-blaziken-ex-b1-greninja-a1",
"winRate": 53.16,
"share": 3.30
},
{
"rank": 8,
"name": "Mega Gardevoir ex Mega Diancie ex",
"usage": 2.83,
"winrate": 43.48,
"record": "440-554-18",
"move": "same",
"limitless": "mega-gardevoir-ex-b2-mega-diancie-ex-b3b",
"winRate": 43.48,
"share": 2.83
},
{
"rank": 9,
"name": "Hydreigon Mega Sableye ex",
"usage": 2.42,
"winrate": 49.74,
"record": "486-475-16",
"move": "same",
"limitless": "hydreigon-b1-mega-sableye-ex-b3b",
"winRate": 49.74,
"share": 2.42
},
{
"rank": 10,
"name": "Mega Altaria ex Espeon",
"usage": 2.29,
"winrate": 52.95,
"record": "511-425-29",
"move": "same",
"limitless": "mega-altaria-ex-b1-espeon-b3a",
"winRate": 52.95,
"share": 2.29
}
],
"topWinrate": [
{
"rank": 1,
"name": "Giratina ex Darkrai ex",
"winrate": 55.17,
"usage": 0.55,
"record": "144-107-10",
"winRate": 55.17,
"share": 0.55,
"limitless": "giratina-ex-a2b-darkrai-ex-a2"
},
{
"rank": 2,
"name": "Milotic ex Eevee ex",
"winrate": 54.65,
"usage": 0.62,
"record": "141-104-13",
"winRate": 54.65,
"share": 0.62,
"limitless": "milotic-ex-b3b-eevee-ex-a3b"
},
{
"rank": 3,
"name": "Greninja Mega Absol ex",
"winrate": 54.62,
"usage": 0.66,
"record": "142-107-11",
"winRate": 54.62,
"share": 0.66,
"limitless": "greninja-a1-mega-absol-ex-b1"
},
{
"rank": 4,
"name": "Zoroark ex Mega Absol ex",
"winrate": 53.72,
"usage": 1.47,
"record": "339-270-22",
"winRate": 53.72,
"share": 1.47,
"limitless": "zoroark-ex-b3-mega-absol-ex-b1"
},
{
"rank": 5,
"name": "Mega Blaziken ex Greninja",
"winrate": 53.16,
"usage": 3.30,
"record": "766-632-43",
"winRate": 53.16,
"share": 3.30,
"limitless": "mega-blaziken-ex-b1-greninja-a1"
},
{
"rank": 6,
"name": "Miraidon ex Magnezone",
"winrate": 52.98,
"usage": 10.17,
"record": "2340-1914-163",
"winRate": 52.98,
"share": 10.17,
"limitless": "miraidon-ex-b3a-magnezone-b1a"
},
{
"rank": 7,
"name": "Mega Altaria ex Espeon",
"winrate": 52.95,
"usage": 2.29,
"record": "511-425-29",
"winRate": 52.95,
"share": 2.29,
"limitless": "mega-altaria-ex-b1-espeon-b3a"
},
{
"rank": 8,
"name": "Gourgeist Houndstone",
"winrate": 52.75,
"usage": 0.39,
"record": "96-81-5",
"winRate": 52.75,
"share": 0.39,
"limitless": "gourgeist-b2-houndstone-b2a"
},
{
"rank": 9,
"name": "Suicune ex Baxcalibur",
"winrate": 52.62,
"usage": 6.37,
"record": "1415-1183-91",
"winRate": 52.62,
"share": 6.37,
"limitless": "suicune-ex-a4a-baxcalibur-b2a"
},
{
"rank": 10,
"name": "Magnezone ex Magnezone",
"winrate": 52.38,
"usage": 0.43,
"record": "110-91-9",
"winRate": 52.38,
"share": 0.43,
"limitless": "magnezone-ex-b3-magnezone-b1a"
}
],
"enteringMeta": [
"Giratina ex Darkrai ex (0,55 % usage, 55,17 % WR — nouveau meilleur winrate du méta, en tête devant les leaders d'hier)",
"Gourgeist Houndstone (0,39 % usage, 52,75 % WR — entre pour la première fois dans le top 10 winrate)",
"Magnezone ex Magnezone (0,43 % usage, 52,38 % WR — entre pour la première fois dans le top 10 winrate)",
"Milotic ex Eevee ex (0,62 % usage, 54,65 % WR — recule à la 2e place mais reste stable en usage)"
],
"leavingMeta": [
"Mega Sceptile ex Greninja (52,27 % WR, 6,20 % usage — sort du top 10 winrate malgré une 4e place stable en usage)",
"Magnezone Miraidon ex (52,06 % WR, 0,86 % usage — sort du top 10 winrate, dépassé par les nouveaux arrivants)",
"Mega Manectric ex Zeraora (51,71 % WR, 0,94 % usage — sort du top 10 winrate)",
"Greninja Mega Sableye ex (2e place usage à 6,51 % mais winrate toujours le point faible du top 3, 47,19 %)"
],
"movements": [
{
"slug": "miraidon-ex-b3a-magnezone-b1a",
"name": "Miraidon ex Magnezone",
"rank": 1,
"usage": 10.17,
"move": "same"
},
{
"slug": "greninja-a1-mega-sableye-ex-b3b",
"name": "Greninja Mega Sableye ex",
"rank": 2,
"usage": 6.51,
"move": "same"
},
{
"slug": "suicune-ex-a4a-baxcalibur-b2a",
"name": "Suicune ex Baxcalibur",
"rank": 3,
"usage": 6.37,
"move": "same"
},
{
"slug": "mega-sceptile-ex-b3-greninja-a1",
"name": "Mega Sceptile ex Greninja",
"rank": 4,
"usage": 6.20,
"move": "same"
},
{
"slug": "mega-lucario-ex-b3-lucario-a2",
"name": "Mega Lucario ex Lucario",
"rank": 5,
"usage": 5.14,
"move": "same"
},
{
"slug": "butterfree-b3b-mega-sceptile-ex-b3",
"name": "Butterfree Mega Sceptile ex",
"rank": 6,
"usage": 3.84,
"move": "same"
},
{
"slug": "mega-blaziken-ex-b1-greninja-a1",
"name": "Mega Blaziken ex Greninja",
"rank": 7,
"usage": 3.30,
"move": "same"
},
{
"slug": "mega-gardevoir-ex-b2-mega-diancie-ex-b3b",
"name": "Mega Gardevoir ex Mega Diancie ex",
"rank": 8,
"usage": 2.83,
"move": "same"
},
{
"slug": "hydreigon-b1-mega-sableye-ex-b3b",
"name": "Hydreigon Mega Sableye ex",
"rank": 9,
"usage": 2.42,
"move": "same"
},
{
"slug": "mega-altaria-ex-b1-espeon-b3a",
"name": "Mega Altaria ex Espeon",
"rank": 10,
"usage": 2.29,
"move": "same"
}
],
"totalDecks": 7631,
"updatedAt": "2026-07-23T15:30:00.000Z",
"topDecks": [
{
"rank": 1,
"name": "Miraidon ex Magnezone",
"usage": 10.17,
"winrate": 52.98,
"record": "2340-1914-163",
"winRate": 52.98,
"share": 10.17,
"move": "same",
"limitless": "miraidon-ex-b3a-magnezone-b1a",
"listBy": "Tornado1",
"cards": {
"pokemon": [
{ "q": 2, "n": "Magnemite", "set": "B1a-24" },
{ "q": 2, "n": "Magneton", "set": "A1-98" },
{ "q": 1, "n": "Magnezone", "set": "B1a-26" },
{ "q": 2, "n": "Miraidon ex", "set": "B3a-19" },
{ "q": 2, "n": "Zeraora", "set": "A3a-21" }
],
"trainers": [
{ "q": 2, "n": "Professor's Research" },
{ "q": 1, "n": "Professor Turo" },
{ "q": 1, "n": "Copycat" },
{ "q": 1, "n": "Cyrus" },
{ "q": 1, "n": "Lisia" },
{ "q": 1, "n": "Clemont" },
{ "q": 1, "n": "Sabrina" },
{ "q": 2, "n": "Poké Ball" },
{ "q": 1, "n": "Giant Cape" }
],
"energy": []
}
},
{
"rank": 2,
"name": "Greninja Mega Sableye ex",
"usage": 6.51,
"winrate": 47.19,
"record": "1224-1295-75",
"winRate": 47.19,
"share": 6.51,
"move": "same",
"limitless": "greninja-a1-mega-sableye-ex-b3b",
"listBy": "𝑻𝑩 / Hasalf",
"cards": {
"pokemon": [
{ "q": 2, "n": "Froakie", "set": "A1-87" },
{ "q": 2, "n": "Greninja", "set": "A1-89" },
{ "q": 2, "n": "Chingling", "set": "B1-109" },
{ "q": 1, "n": "Mega Absol ex", "set": "B1-151" },
{ "q": 1, "n": "Darkrai ex", "set": "A2-110" },
{ "q": 1, "n": "Mega Sableye ex", "set": "B3b-41" }
],
"trainers": [
{ "q": 2, "n": "Professor's Research" },
{ "q": 2, "n": "Copycat" },
{ "q": 1, "n": "Cyrus" },
{ "q": 2, "n": "Poké Ball" },
{ "q": 2, "n": "Rare Candy" },
{ "q": 1, "n": "Small Balloon" },
{ "q": 1, "n": "Lucky Egg" }
],
"energy": []
}
},
{
"rank": 3,
"name": "Suicune ex Baxcalibur",
"usage": 6.37,
"winrate": 52.62,
"record": "1415-1183-91",
"winRate": 52.62,
"share": 6.37,
"move": "same",
"limitless": "suicune-ex-a4a-baxcalibur-b2a",
"listBy": "・",
"cards": {
"pokemon": [
{ "q": 2, "n": "Frigibax", "set": "B2a-34" },
{ "q": 2, "n": "Baxcalibur", "set": "B2a-36" },
{ "q": 2, "n": "Suicune ex", "set": "A4a-20" },
{ "q": 1, "n": "Chien-Pao ex", "set": "B2a-37" }
],
"trainers": [
{ "q": 2, "n": "Professor's Research" },
{ "q": 2, "n": "Copycat" },
{ "q": 1, "n": "Pokémon Center Lady" },
{ "q": 2, "n": "Poké Ball" },
{ "q": 2, "n": "Rare Candy" },
{ "q": 2, "n": "Giant Cape" },
{ "q": 1, "n": "Inflatable Boat" },
{ "q": 1, "n": "Starting Plains" }
],
"energy": []
}
},
{
"rank": 4,
"name": "Mega Sceptile ex Greninja",
"usage": 6.20,
"winrate": 52.27,
"record": "1403-1198-83",
"winRate": 52.27,
"share": 6.20,
"move": "same",
"limitless": "mega-sceptile-ex-b3-greninja-a1",
"listBy": "𝗕𝗢𝗔𝗧 | Koe",
"cards": {
"pokemon": [
{ "q": 2, "n": "Treecko", "set": "B3-5" },
{ "q": 1, "n": "Grovyle", "set": "B3-6" },
{ "q": 1, "n": "Mega Sceptile ex", "set": "B3-8" },
{ "q": 1, "n": "Froakie", "set": "A1-87" },
{ "q": 1, "n": "Greninja", "set": "A1-89" },
{ "q": 1, "n": "Pheromosa", "set": "A3a-7" },
{ "q": 1, "n": "Furfrou", "set": "B3b-61" }
],
"trainers": [
{ "q": 2, "n": "Professor's Research" },
{ "q": 2, "n": "Copycat" },
{ "q": 1, "n": "Cyrus" },
{ "q": 1, "n": "Juliana" },
{ "q": 2, "n": "Poké Ball" },
{ "q": 2, "n": "Rare Candy" },
{ "q": 1, "n": "Small Balloon" },
{ "q": 1, "n": "Rocky Helmet" }
],
"energy": []
}
},
{
"rank": 5,
"name": "Mega Lucario ex Lucario",
"usage": 5.14,
"winrate": 50.78,
"record": "1138-1020-83",
"winRate": 50.78,
"share": 5.14,
"move": "same",
"limitless": "mega-lucario-ex-b3-lucario-a2",
"listBy": "Hansuwe",
"cards": {
"pokemon": [
{ "q": 1, "n": "Riolu", "set": "A2-91" },
{ "q": 1, "n": "Riolu", "set": "B3-79" },
{ "q": 2, "n": "Mega Lucario ex", "set": "B3-81" },
{ "q": 1, "n": "Lucario", "set": "A2-92" },
{ "q": 1, "n": "Hitmonlee", "set": "A1-154" },
{ "q": 1, "n": "Zygarde", "set": "P-B-51" }
],
"trainers": [
{ "q": 2, "n": "Professor's Research" },
{ "q": 1, "n": "Sabrina" },
{ "q": 1, "n": "Cyrus" },
{ "q": 1, "n": "Pokémon Center Lady" },
{ "q": 1, "n": "Copycat" },
{ "q": 1, "n": "Korrina" },
{ "q": 2, "n": "Poké Ball" },
{ "q": 1, "n": "X Speed" },
{ "q": 1, "n": "Rocky Helmet" },
{ "q": 1, "n": "Protective Poncho" },
{ "q": 1, "n": "Arena of Antiquity" }
],
"energy": []
}
},
{
"rank": 6,
"name": "Butterfree Mega Sceptile ex",
"usage": 3.84,
"winrate": 48.08,
"record": "752-765-47",
"winRate": 48.08,
"share": 3.84,
"move": "same",
"limitless": "butterfree-b3b-mega-sceptile-ex-b3",
"listBy": "AndrewBreaker",
"cards": {
"pokemon": [
{ "q": 2, "n": "Caterpie", "set": "B3b-1" },
{ "q": 2, "n": "Metapod", "set": "B3b-2" },
{ "q": 2, "n": "Butterfree", "set": "B3b-3" },
{ "q": 1, "n": "Treecko", "set": "B3-5" },
{ "q": 1, "n": "Grovyle", "set": "B3-6" },
{ "q": 1, "n": "Mega Sceptile ex", "set": "B3-8" }
],
"trainers": [
{ "q": 2, "n": "Professor's Research" },
{ "q": 1, "n": "Copycat" },
{ "q": 1, "n": "Cyrus" },
{ "q": 1, "n": "Giovanni" },
{ "q": 2, "n": "Quick-Grow Extract" },
{ "q": 1, "n": "X Speed" },
{ "q": 1, "n": "Leaf Cape" },
{ "q": 2, "n": "Fragrant Forest" }
],
"energy": []
}
},
{
"rank": 7,
"name": "Mega Blaziken ex Greninja",
"usage": 3.30,
"winrate": 53.16,
"record": "766-632-43",
"winRate": 53.16,
"share": 3.30,
"move": "same",
"limitless": "mega-blaziken-ex-b1-greninja-a1",
"listBy": "Banzai",
"cards": {
"pokemon": [
{ "q": 2, "n": "Torchic", "set": "B1-33" },
{ "q": 1, "n": "Combusken", "set": "B1-34" },
{ "q": 1, "n": "Mega Blaziken ex", "set": "B1-36" },
{ "q": 1, "n": "Froakie", "set": "A1-87" },
{ "q": 1, "n": "Greninja", "set": "A1-89" },
{ "q": 1, "n": "Castform Sunny Form", "set": "B3-24" },
{ "q": 1, "n": "Heatmor", "set": "B1-44" }
],
"trainers": [
{ "q": 2, "n": "Copycat" },
{ "q": 2, "n": "Professor's Research" },
{ "q": 1, "n": "Cyrus" },
{ "q": 1, "n": "Juliana" },
{ "q": 2, "n": "Rare Candy" },
{ "q": 2, "n": "Poké Ball" },
{ "q": 1, "n": "Flame Patch" },
{ "q": 1, "n": "Hiking Trail" }
],
"energy": []
}
},
{
"rank": 8,
"name": "Mega Gardevoir ex Mega Diancie ex",
"usage": 2.83,
"winrate": 43.48,
"record": "440-554-18",
"winRate": 43.48,
"share": 2.83,
"move": "same",
"limitless": "mega-gardevoir-ex-b2-mega-diancie-ex-b3b",
"listBy": "sleepy512pete",
"cards": {
"pokemon": [
{ "q": 2, "n": "Ralts", "set": "B2-63" },
{ "q": 1, "n": "Mega Gardevoir ex", "set": "B2-66" },
{ "q": 1, "n": "Gardevoir", "set": "B2-65" },
{ "q": 2, "n": "Carbink", "set": "B3b-31" },
{ "q": 1, "n": "Mega Diancie ex", "set": "B3b-32" }
],
"trainers": [
{ "q": 2, "n": "Professor's Research" },
{ "q": 2, "n": "Diantha" },
{ "q": 1, "n": "Sabrina" },
{ "q": 1, "n": "Copycat" },
{ "q": 1, "n": "Serena" },
{ "q": 2, "n": "Poké Ball" },
{ "q": 2, "n": "Rare Candy" },
{ "q": 1, "n": "Protective Poncho" },
{ "q": 1, "n": "Peculiar Plaza" }
],
"energy": []
}
},
{
"rank": 9,
"name": "Hydreigon Mega Sableye ex",
"usage": 2.42,
"winrate": 49.74,
"record": "486-475-16",
"winRate": 49.74,
"share": 2.42,
"move": "same",
"limitless": "hydreigon-b1-mega-sableye-ex-b3b",
"listBy": "JLNG",
"cards": {
"pokemon": [
{ "q": 2, "n": "Deino", "set": "B1-155" },
{ "q": 2, "n": "Hydreigon", "set": "B1-157" },
{ "q": 1, "n": "Mega Sableye ex", "set": "B3b-41" },
{ "q": 1, "n": "Bombirdier", "set": "B3-115" }
],
"trainers": [
{ "q": 2, "n": "Professor's Research" },
{ "q": 2, "n": "Copycat" },
{ "q": 1, "n": "Sabrina" },
{ "q": 1, "n": "Cyrus" },
{ "q": 2, "n": "Poké Ball" },
{ "q": 2, "n": "Rare Candy" },
{ "q": 2, "n": "Lucky Ice Pop" },
{ "q": 2, "n": "Rocky Helmet" }
],
"energy": []
}
},
{
"rank": 10,
"name": "Mega Altaria ex Espeon",
"usage": 2.29,
"winrate": 52.95,
"record": "511-425-29",
"winRate": 52.95,
"share": 2.29,
"move": "same",
"limitless": "mega-altaria-ex-b1-espeon-b3a",
"listBy": "Feyyzo",
"cards": {
"pokemon": [
{ "q": 2, "n": "Swablu", "set": "B1-196" },
{ "q": 1, "n": "Mega Altaria ex", "set": "B1-102" },
{ "q": 2, "n": "Eevee", "set": "B1-184" },
{ "q": 2, "n": "Espeon", "set": "B3a-20" },
{ "q": 2, "n": "Darkrai", "set": "B2b-40" },
{ "q": 2, "n": "Igglybuff", "set": "A4a-59" }
],
"trainers": [
{ "q": 2, "n": "Professor's Research" },
{ "q": 1, "n": "Cyrus" },
{ "q": 1, "n": "Copycat" },
{ "q": 1, "n": "Lisia" },
{ "q": 1, "n": "Sabrina" },
{ "q": 2, "n": "Poké Ball" },
{ "q": 1, "n": "Training Area" }
],
"energy": []
}
},
{
"rank": 38,
"name": "Giratina ex Darkrai ex",
"usage": 0.55,
"winrate": 55.17,
"record": "144-107-10",
"winRate": 55.17,
"share": 0.55,
"move": "new",
"limitless": "giratina-ex-a2b-darkrai-ex-a2",
"listBy": "𝗠𝗮𝗴𝗺𝗮 TheViice",
"cards": {
"pokemon": [
{ "q": 2, "n": "Giratina ex", "set": "A2b-35" },
{ "q": 2, "n": "Darkrai ex", "set": "A2-110" },
{ "q": 1, "n": "Indeedee ex", "set": "B1-121" }
],
"trainers": [
{ "q": 2, "n": "Copycat" },
{ "q": 1, "n": "Professor's Research" },
{ "q": 1, "n": "Cyrus" },
{ "q": 1, "n": "Sabrina" },
{ "q": 1, "n": "Red" },
{ "q": 2, "n": "Poké Ball" },
{ "q": 1, "n": "Lucky Ice Pop" },
{ "q": 1, "n": "Field Blower" },
{ "q": 2, "n": "Rocky Helmet" },
{ "q": 1, "n": "Giant Cape" },
{ "q": 1, "n": "Starting Plains" },
{ "q": 1, "n": "Peculiar Plaza" }
],
"energy": []
}
},
{
"rank": 33,
"name": "Milotic ex Eevee ex",
"usage": 0.62,
"winrate": 54.65,
"record": "141-104-13",
"winRate": 54.65,
"share": 0.62,
"move": "same",
"limitless": "milotic-ex-b3b-eevee-ex-a3b",
"listBy": "JLNG",
"cards": {
"pokemon": [
{ "q": 2, "n": "Feebas", "set": "A4a-21" },
{ "q": 2, "n": "Milotic ex", "set": "B3b-15" },
{ "q": 1, "n": "Chien-Pao ex", "set": "B2a-37" },
{ "q": 1, "n": "Vaporeon", "set": "A1a-19" },
{ "q": 1, "n": "Eevee ex", "set": "A3b-56" }
],
"trainers": [
{ "q": 2, "n": "Wallace" },
{ "q": 2, "n": "Professor's Research" },
{ "q": 2, "n": "Copycat" },
{ "q": 1, "n": "Pokémon Center Lady" },
{ "q": 2, "n": "Poké Ball" },
{ "q": 1, "n": "Field Blower" },
{ "q": 1, "n": "Giant Cape" },
{ "q": 1, "n": "Elegant Cape" },
{ "q": 1, "n": "Training Area" }
],
"energy": []
}
},
{
"rank": 32,
"name": "Greninja Mega Absol ex",
"usage": 0.66,
"winrate": 54.62,
"record": "142-107-11",
"winRate": 54.62,
"share": 0.66,
"move": "same",
"limitless": "greninja-a1-mega-absol-ex-b1",
"listBy": "𝗕𝗢𝗔𝗧 | Toxology",
"cards": {
"pokemon": [
{ "q": 2, "n": "Froakie", "set": "A1-87" },
{ "q": 2, "n": "Greninja", "set": "A1-89" },
{ "q": 2, "n": "Chingling", "set": "B1-109" },
{ "q": 1, "n": "Darkrai ex", "set": "A2-110" },
{ "q": 1, "n": "Mega Absol ex", "set": "B1-151" }
],
"trainers": [
{ "q": 2, "n": "Professor's Research" },
{ "q": 2, "n": "Copycat" },
{ "q": 1, "n": "Cyrus" },
{ "q": 2, "n": "Rare Candy" },
{ "q": 2, "n": "Poké Ball" },
{ "q": 1, "n": "Rocky Helmet" },
{ "q": 1, "n": "Inflatable Boat" },
{ "q": 1, "n": "Lucky Egg" }
],
"energy": []
}
}
],
"news": [
{
"title": "\"Ruler of the Skies set dropping in a few days, save your resources\" : discussion communautaire sur la préparation à l'arrivée de B4",
"url": "https://www.reddit.com/r/PTCGP/comments/1v2kdup/ruler_of_the_skies_set_dropping_in_a_few_days/",
"source": "Reddit r/PTCGP",
"kind": "article",
"date": "22 juillet 2026"
},
{
"title": "Everyday Life Surrounded by Puppy Pokémon | Pokémon TCG Pocket",
"url": "https://www.youtube.com/watch?v=vokUdvZJWPA",
"source": "The Official Pokémon YouTube channel",
"kind": "video",
"date": "22 juillet 2026"
},
{
"title": "Hisuian Zorua Drop Event : événement PvE en cours jusqu'au 26 juillet 2026 (guide des meilleurs decks pour le contrer)",
"url": "https://game8.co/games/Pokemon-TCG-Pocket/archives/608923",
"source": "Game8",
"kind": "article",
"date": "16 juillet 2026"
},
{
"title": "Ruler of the Skies (B4) confirmée pour le 30 juillet 2026 : Mega Rayquaza ex en vedette",
"url": "https://game8.co/games/Pokemon-TCG-Pocket/archives/605801",
"source": "Game8",
"kind": "article",
"date": "juillet 2026"
},
{
"title": "\"3 Seasons In A Row: Easiest Season Yet (75% WR)\" : retour d'expérience communautaire sur un deck performant en classé",
"url": "https://www.reddit.com/r/PTCGP/comments/1v0icey/3_seasons_in_a_row_easiest_season_yet_75_wr/",
"source": "Reddit r/PTCGP",
"kind": "article",
"date": "19 juillet 2026"
},
{
"title": "Pokémon TCG Pocket : programme du Premium Pass de juillet 2026 (promo Psyduck, accessoires Piplup)",
"url": "https://pokemongohub.net/post/tcg-pocket/pokemon-tcg-pocket-july-2026-premium-pass-lineup-missions/",
"source": "Pokémon GO Hub",
"kind": "article",
"date": "30 juin 2026"
},
{
"title": "Everyday Wonders : la mini-extension (B3b) est disponible depuis le 29 juin (Mega Diancie ex en carte phare)",
"url": "https://www.pokemon.com/us/news/pokemon-tcg-pocket-everyday-wonders-expansion-is-now-available",
"source": "Pokemon.com (officiel)",
"kind": "article",
"date": "29 juin 2026"
},
{
"title": "JCC Pokémon Pocket : Jours Heureux | Bande-annonce officielle",
"url": "https://www.youtube.com/watch?v=ZhBDrLKktqc",
"source": "La chaîne officielle Pokémon en français",
"kind": "video",
"date": "25 juin 2026"
}
]
}
